junit2influx/__init__.py
junit2influx/cli.py
junit2influx/client.py
junit2influx/xunitparser.py
junit2influx-0.2.1.dist-info/DESCRIPTION.rst
junit2influx-0.2.1.dist-info/METADATA
junit2influx-0.2.1.dist-info/RECORD
junit2influx-0.2.1.dist-info/WHEEL
junit2influx-0.2.1.dist-info/entry_points.txt
junit2influx-0.2.1.dist-info/metadata.json
junit2influx-0.2.1.dist-info/top_level.txt
junit2influx-0.2.1.dist-info/zip-safe
