Metadata-Version: 2.0
Name: junit2influx
Version: 0.2.1
Summary: "Send junit data to influxdb"
Home-page: UNKNOWN
Author: Eliot Berriot
Author-email: eliot.berriot@people-doc.com
License: MIT
Keywords: code,monitoring,tests,database,xml
Platform: UNKNOWN
Classifier: Development Status :: 4 - Beta
Classifier: Intended Audience :: Developers
Classifier: License :: OSI Approved :: MIT License
Classifier: Natural Language :: English
Classifier: Programming Language :: Python :: 2
Classifier: Programming Language :: Python :: 2.7
Classifier: Programming Language :: Python :: 3
Classifier: Programming Language :: Python :: 3.4
Classifier: Programming Language :: Python :: 3.5
Requires-Dist: influxdb
Requires-Dist: click
Provides-Extra: dev
Requires-Dist: pytest; extra == 'dev'
Requires-Dist: wheel; extra == 'dev'
Requires-Dist: zest.releaser[recommended]; extra == 'dev'
Requires-Dist: pyroma (==2.0); extra == 'dev'
Provides-Extra: lint
Requires-Dist: prospector[with_pyroma]; extra == 'lint'
Provides-Extra: test
Requires-Dist: pytest; extra == 'test'
Requires-Dist: pytest-cov; extra == 'test'
Requires-Dist: pytest-mock; extra == 'test'
